intro/__init__.py
intro/intro.py
news/__init__.py
news/core.py
news/thread.py
setup/__init__.py
setup/install.py
webcam/__init__.py
aij_webcam-1.1.10.dist-info/LICENSE.txt
aij_webcam-1.1.10.dist-info/METADATA
aij_webcam-1.1.10.dist-info/WHEEL
aij_webcam-1.1.10.dist-info/entry_points.txt
aij_webcam-1.1.10.dist-info/top_level.txt
aij_webcam-1.1.10.dist-info/RECORD
