Metadata-Version: 2.1
Name: aij-webcam
Version: 1.1.10
Summary: AI Journalist GUI Application
Author-email: Yilmaz Mustafa <dev@mail.be>
License: Copyright (c) 2016 The Python Packaging Authority (PyPA)
Project-URL: Homepage, https://www.codesapien.be/aij/
Project-URL: Bug Reports, https://github.com/codesapienbe/aij-webcam/issues
Project-URL: Funding, https://donate.pypi.org
Project-URL: Say Thanks!, http://saythanks.io/to/aij
Project-URL: Source, https://github.com/codesapienbe/aij-webcam
Keywords: aij,setuptools,development
Classifier: Development Status :: 3 - Alpha
Classifier: Intended Audience :: Developers
Classifier: Topic :: Software Development :: Build Tools
Classifier: License :: OSI Approved :: MIT License
Classifier: Programming Language :: Python :: 3
Classifier: Programming Language :: Python :: 3.7
Classifier: Programming Language :: Python :: 3.8
Classifier: Programming Language :: Python :: 3.9
Classifier: Programming Language :: Python :: 3.10
Classifier: Programming Language :: Python :: 3.11
Classifier: Programming Language :: Python :: 3 :: Only
Requires-Python: >=3.7
License-File: LICENSE.txt
Requires-Dist: requests
Requires-Dist: setuptools
Requires-Dist: wheel
Requires-Dist: pipenv
Requires-Dist: pylint
Requires-Dist: autopep8
Requires-Dist: pyinstaller
Requires-Dist: pytest
Requires-Dist: pytest-cov
Requires-Dist: opencv-python
Requires-Dist: mediapipe
Requires-Dist: pandas
Requires-Dist: gtts
Requires-Dist: pygame
Requires-Dist: cairosvg
Requires-Dist: pika
Provides-Extra: dev
Requires-Dist: check-manifest ; extra == 'dev'
Provides-Extra: test
Requires-Dist: coverage ; extra == 'test'
